SonnoiiKub/EDA.py
SonnoiiKub/__init__.py
SonnoiiKub/calculator.py
SonnoiiKub-0.1.0.dist-info/LICENCE.txt
SonnoiiKub-0.1.0.dist-info/METADATA
SonnoiiKub-0.1.0.dist-info/WHEEL
SonnoiiKub-0.1.0.dist-info/top_level.txt
SonnoiiKub-0.1.0.dist-info/RECORD
